{"nodes": [{"id": "validate_ga_controls_py", "label": "validate_ga_controls.py", "file_type": "code", "source_file": "validate_ga_controls.py", "source_location": "L1"}, {"id": "validate_ga_controls_create_test_problem", "label": "create_test_problem()", "file_type": "code", "source_file": "validate_ga_controls.py", "source_location": "L31"}, {"id": "validate_ga_controls_test_service_ga", "label": "test_service_ga()", "file_type": "code", "source_file": "validate_ga_controls.py", "source_location": "L62"}, {"id": "validate_ga_controls_test_frequency_ga", "label": "test_frequency_ga()", "file_type": "code", "source_file": "validate_ga_controls.py", "source_location": "L90"}, {"id": "validate_ga_controls_validate_ga_controls", "label": "validate_ga_controls()", "file_type": "code", "source_file": "validate_ga_controls.py", "source_location": "L122"}, {"id": "validate_ga_controls_rationale_32", "label": "Create a minimal test problem for GA testing.", "file_type": "rationale", "source_file": "validate_ga_controls.py", "source_location": "L32"}, {"id": "validate_ga_controls_rationale_63", "label": "Test ServiceGA with control fixes.", "file_type": "rationale", "source_file": "validate_ga_controls.py", "source_location": "L63"}, {"id": "validate_ga_controls_rationale_91", "label": "Test FrequencyGA with control fixes.", "file_type": "rationale", "source_file": "validate_ga_controls.py", "source_location": "L91"}, {"id": "validate_ga_controls_rationale_123", "label": "Validate GA control behavior.", "file_type": "rationale", "source_file": "validate_ga_controls.py", "source_location": "L123"}], "edges": [{"source": "validate_ga_controls_py", "target": "json", "relation": "imports", "confidence": "EXTRACTED", "source_file": "validate_ga_controls.py", "source_location": "L9", "weight": 1.0}, {"source": "validate_ga_controls_py", "target": "sys", "relation": "imports", "confidence": "EXTRACTED", "source_file": "validate_ga_controls.py", "source_location": "L10", "weight": 1.0}, {"source": "validate_ga_controls_py", "target": "time", "relation": "imports", "confidence": "EXTRACTED", "source_file": "validate_ga_controls.py", "source_location": "L11", "weight": 1.0}, {"source": "validate_ga_controls_py", "target": "logging", "relation": "imports", "confidence": "EXTRACTED", "source_file": "validate_ga_controls.py", "source_location": "L12", "weight": 1.0}, {"source": "validate_ga_controls_py", "target": "pathlib", "relation": "imports_from", "confidence": "EXTRACTED", "source_file": "validate_ga_controls.py", "source_location": "L13", "weight": 1.0}, {"source": "validate_ga_controls_py", "target": "typing", "relation": "imports_from", "confidence": "EXTRACTED", "source_file": "validate_ga_controls.py", "source_location": "L14", "weight": 1.0}, {"source": "validate_ga_controls_py", "target": "src_optimization_service_ga", "relation": "imports_from", "confidence": "EXTRACTED", "source_file": "validate_ga_controls.py", "source_location": "L19", "weight": 1.0}, {"source": "validate_ga_controls_py", "target": "src_optimization_frequency_ga", "relation": "imports_from", "confidence": "EXTRACTED", "source_file": "validate_ga_controls.py", "source_location": "L20", "weight": 1.0}, {"source": "validate_ga_controls_py", "target": "src_optimization_data", "relation": "imports_from", "confidence": "EXTRACTED", "source_file": "validate_ga_controls.py", "source_location": "L21", "weight": 1.0}, {"source": "validate_ga_controls_py", "target": "validate_ga_controls_create_test_problem", "relation": "contains", "confidence": "EXTRACTED", "source_file": "validate_ga_controls.py", "source_location": "L31", "weight": 1.0}, {"source": "validate_ga_controls_py", "target": "validate_ga_controls_test_service_ga", "relation": "contains", "confidence": "EXTRACTED", "source_file": "validate_ga_controls.py", "source_location": "L62", "weight": 1.0}, {"source": "validate_ga_controls_py", "target": "validate_ga_controls_test_frequency_ga", "relation": "contains", "confidence": "EXTRACTED", "source_file": "validate_ga_controls.py", "source_location": "L90", "weight": 1.0}, {"source": "validate_ga_controls_py", "target": "validate_ga_controls_validate_ga_controls", "relation": "contains", "confidence": "EXTRACTED", "source_file": "validate_ga_controls.py", "source_location": "L122", "weight": 1.0}, {"source": "validate_ga_controls_test_service_ga", "target": "validate_ga_controls_create_test_problem", "relation": "calls", "confidence": "EXTRACTED", "source_file": "validate_ga_controls.py", "source_location": "L66", "weight": 1.0}, {"source": "validate_ga_controls_test_frequency_ga", "target": "validate_ga_controls_create_test_problem", "relation": "calls", "confidence": "EXTRACTED", "source_file": "validate_ga_controls.py", "source_location": "L94", "weight": 1.0}, {"source": "validate_ga_controls_validate_ga_controls", "target": "validate_ga_controls_test_service_ga", "relation": "calls", "confidence": "EXTRACTED", "source_file": "validate_ga_controls.py", "source_location": "L129", "weight": 1.0}, {"source": "validate_ga_controls_validate_ga_controls", "target": "validate_ga_controls_test_frequency_ga", "relation": "calls", "confidence": "EXTRACTED", "source_file": "validate_ga_controls.py", "source_location": "L132", "weight": 1.0}, {"source": "validate_ga_controls_rationale_32", "target": "validate_ga_controls_create_test_problem", "relation": "rationale_for", "confidence": "EXTRACTED", "source_file": "validate_ga_controls.py", "source_location": "L32", "weight": 1.0}, {"source": "validate_ga_controls_rationale_63", "target": "validate_ga_controls_test_service_ga", "relation": "rationale_for", "confidence": "EXTRACTED", "source_file": "validate_ga_controls.py", "source_location": "L63", "weight": 1.0}, {"source": "validate_ga_controls_rationale_91", "target": "validate_ga_controls_test_frequency_ga", "relation": "rationale_for", "confidence": "EXTRACTED", "source_file": "validate_ga_controls.py", "source_location": "L91", "weight": 1.0}, {"source": "validate_ga_controls_rationale_123", "target": "validate_ga_controls_validate_ga_controls", "relation": "rationale_for", "confidence": "EXTRACTED", "source_file": "validate_ga_controls.py", "source_location": "L123", "weight": 1.0}]}